slickpay/__init__.py
slickpay/aggregationPayment.py
slickpay/transfer.py
slick_pay_python-0.3.dist-info/LICENSE
slick_pay_python-0.3.dist-info/METADATA
slick_pay_python-0.3.dist-info/WHEEL
slick_pay_python-0.3.dist-info/top_level.txt
slick_pay_python-0.3.dist-info/RECORD
